gtfs_utils/__init__.py
gtfs_utils/__main__.py
gtfs_utils/filter.py
gtfs_utils/info.py
gtfs_utils/remove_shapes.py
gtfs_utils/utils.py
gtfs_utils/cli/__init__.py
gtfs_utils/cli/app.py
gtfs_utils/cli/cli_utils.py
gtfs_utils/cli/filter.py
gtfs_utils/cli/info.py
gtfsutils-0.2.1.dist-info/licenses/LICENSE
gtfsutils-0.2.1.dist-info/METADATA
gtfsutils-0.2.1.dist-info/WHEEL
gtfsutils-0.2.1.dist-info/entry_points.txt
gtfsutils-0.2.1.dist-info/top_level.txt
gtfsutils-0.2.1.dist-info/RECORD
