Metadata-Version: 2.4
Name: gtfsutils
Version: 0.2.1
Summary: Utility library for working with gtfs files
Author-email: Luis Nachtigall <l.nachtigall@triply.at>, Chris Stelzmüller <c.stelzmueller@triply.at>
Project-URL: Repository, https://github.com/triply-at/gtfs-utils.git
Project-URL: Issues, https://github.com/triply-at/gtfs-utils/issues
Classifier: Programming Language :: Python :: 3
Classifier: Operating System :: OS Independent
Requires-Python: >=3.10
License-File: LICENSE
Requires-Dist: dask[dataframe]>=2025.2.0
Requires-Dist: geopandas>=1.0.1
Requires-Dist: numpy>=2.2.4
Requires-Dist: pandas>=2.2.3
Requires-Dist: rich>=13.9.4
Requires-Dist: shapely>=2.0.7
Requires-Dist: typer>=0.15.2
Provides-Extra: maps
Requires-Dist: folium>=0.19.5; extra == "maps"
Requires-Dist: mapclassify>=2.8.1; extra == "maps"
Requires-Dist: matplotlib>=3.10.1; extra == "maps"
Dynamic: license-file
